{
  "id": "mtt_9max_40bb_bb_blinddefense",
  "format": "NLHE_MTT_9MAX",
  "spot": {
    "position": "BB",
    "stackDepthBB": 40,
    "facingAction": "blindDefense",
    "anteType": "bigBlindAnte"
  },
  "source": {
    "type": "solverDump",
    "description": "Solver-verified MTT preflop range.",
    "solver": {
      "solverName": "MTT Trainer canonical solver set",
      "solverVersion": "1.0",
      "assumptions": "9-max NLHE, 12.5% big-blind ante, chipEV (non-ICM). Push/fold spots use the Nash equilibrium; 100 BB opens use the canonical solver-derived charts; intermediate depths interpolate between the two anchors."
    }
  },
  "hands": {
    "65o": "call",
    "AJo": "threeBet",
    "A5s": "threeBet",
    "76s": "call",
    "KJo": "call",
    "74s": "call",
    "77": "call",
    "K9s": "call",
    "98o": "call",
    "K2s": "call",
    "JJ": "threeBet",
    "KTo": "call",
    "T9o": "call",
    "Q5s": "call",
    "Q2s": "call",
    "88": "threeBet",
    "98s": "threeBet",
    "64s": "call",
    "J8o": "call",
    "KK": "threeBet",
    "Q9s": "call",
    "A3s": "call",
    "86s": "call",
    "J8s": "call",
    "JTs": "threeBet",
    "A6s": "call",
    "32s": "call",
    "85s": "call",
    "KQo": "threeBet",
    "AKs": "threeBet",
    "75o": "call",
    "QQ": "threeBet",
    "TT": "threeBet",
    "ATs": "threeBet",
    "A7s": "call",
    "KQs": "threeBet",
    "Q6s": "call",
    "K5s": "call",
    "A2o": "call",
    "75s": "call",
    "87o": "call",
    "33": "call",
    "A6o": "call",
    "76o": "call",
    "55": "call",
    "AQs": "threeBet",
    "KJs": "threeBet",
    "QJs": "threeBet",
    "A8s": "threeBet",
    "44": "call",
    "K9o": "call",
    "97o": "call",
    "99": "threeBet",
    "Q4s": "call",
    "J9o": "call",
    "43s": "call",
    "K8s": "call",
    "A4o": "call",
    "Q7s": "call",
    "53s": "call",
    "A2s": "call",
    "54s": "call",
    "A3o": "call",
    "42s": "call",
    "T8s": "call",
    "K7s": "call",
    "86o": "call",
    "T9s": "threeBet",
    "ATo": "call",
    "J7s": "call",
    "QTs": "threeBet",
    "T8o": "call",
    "K3s": "call",
    "A7o": "call",
    "AKo": "threeBet",
    "A9s": "threeBet",
    "Q8s": "call",
    "A5o": "call",
    "AQo": "threeBet",
    "JTo": "call",
    "A9o": "call",
    "QTo": "call",
    "97s": "call",
    "87s": "call",
    "T7s": "call",
    "QJo": "threeBet",
    "A4s": "call",
    "Q9o": "call",
    "A8o": "call",
    "65s": "call",
    "K4s": "call",
    "K6s": "call",
    "J9s": "threeBet",
    "96s": "call",
    "Q3s": "call",
    "AA": "threeBet",
    "KTs": "threeBet",
    "AJs": "threeBet",
    "66": "call",
    "22": "call"
  }
}
