{
  "format" : "NLHE_MTT_9MAX",
  "hands" : {
    "22" : {
      "call" : 1
    },
    "33" : {
      "call" : 0.2203,
      "fold" : 0.77969999999999995
    },
    "44" : {
      "call" : 0.1171,
      "fold" : 0.88290000000000002
    },
    "54s" : {
      "call" : 1
    },
    "55" : {
      "call" : 0.066699999999999968,
      "fold" : 0.93330000000000002
    },
    "65s" : {
      "call" : 1
    },
    "66" : {
      "call" : 0.46789999999999998,
      "fold" : 0.53210000000000002
    },
    "76s" : {
      "call" : 1
    },
    "77" : {
      "call" : 0.35589999999999999,
      "fold" : 0.64410000000000001
    },
    "87s" : {
      "call" : 1
    },
    "88" : {
      "call" : 0.54000000000000004,
      "fold" : 0.46000000000000002
    },
    "98s" : {
      "call" : 1
    },
    "99" : {
      "call" : 0.36009999999999998,
      "fold" : 0.63990000000000002
    },
    "A3s" : {
      "raise25x" : 1
    },
    "A4s" : {
      "call" : 0.64600000000000002,
      "raise25x" : 0.35399999999999998
    },
    "A5s" : {
      "call" : 1
    },
    "A6s" : {
      "call" : 0.0057999999999999996,
      "fold" : 0.90029999999999999,
      "raise25x" : 0.093900000000000011
    },
    "A7s" : {
      "fold" : 0.96009999999999995,
      "raise25x" : 0.039899999999999998
    },
    "A8s" : {
      "call" : 0.48609999999999998,
      "fold" : 0.0499,
      "raise25x" : 0.46400000000000002
    },
    "A9s" : {
      "call" : 0.57199999999999995,
      "raise25x" : 0.42799999999999999
    },
    "AA" : {
      "raise25x" : 1
    },
    "AJs" : {
      "call" : 1
    },
    "AKo" : {
      "call" : 0.65010000000000001,
      "raise25x" : 0.34989999999999999
    },
    "AKs" : {
      "call" : 1
    },
    "AQo" : {
      "fold" : 0.98819999999999997,
      "raise25x" : 0.0118
    },
    "AQs" : {
      "call" : 1
    },
    "ATs" : {
      "call" : 1
    },
    "JJ" : {
      "call" : 0.98009999999999997,
      "raise25x" : 0.019899999999999998
    },
    "JTs" : {
      "call" : 0.32200000000000001,
      "fold" : 0.67800000000000005
    },
    "KJs" : {
      "call" : 0.69410000000000005,
      "fold" : 0.23400000000000001,
      "raise25x" : 0.071900000000000019
    },
    "KK" : {
      "call" : 0.71409999999999996,
      "raise25x" : 0.28589999999999999
    },
    "KQs" : {
      "call" : 1
    },
    "KTs" : {
      "fold" : 0.86409999999999998,
      "raise25x" : 0.13589999999999999
    },
    "QJs" : {
      "call" : 0.64410000000000001,
      "fold" : 0.35589999999999999
    },
    "QQ" : {
      "call" : 0.98399999999999999,
      "raise25x" : 0.016
    },
    "QTs" : {
      "call" : 0.30599999999999999,
      "fold" : 0.69399999999999995
    },
    "T9s" : {
      "call" : 1
    },
    "TT" : {
      "call" : 0.69999999999999996,
      "fold" : 0.29999999999999999
    }
  },
  "id" : "mtt_9max_100bb_utg1_vs3bet_vs_bb",
  "source" : {
    "description" : "Adapted from RangeConverter 8-max baseline.",
    "publisher" : {
      "accessedDate" : "2026-06-01",
      "name" : "RangeConverter",
      "product" : "Free Poker Charts — 8 max 1bb ante MTT GTO Ranges",
      "treeParams" : "2.5x open, 3.5x 3bet IP, 4.5x 3bet OOP, 2.3x 4bet IP, 2.75x 4bet OOP, SB vs BB 3.2bb",
      "url" : "https:\/\/rangeconverter.com\/free-poker-charts"
    },
    "solver" : {
      "assumptions" : "Frequencies rounded to nearest 25% per source. ChipEV (non-ICM). 1bb (12.5%) big-blind ante. Adapted from 8-max UTG (9-max UTG+1 plays the same role as 8-max UTG)."
    },
    "type" : "published"
  },
  "spot" : {
    "anteType" : "bigBlindAnte",
    "facingAction" : "vs3Bet",
    "opponentPosition" : "BB",
    "position" : "UTG1",
    "stackDepthBB" : 100
  }
}